mlflow_modal/__init__.py
mlflow_modal/deployment.py
mlflow_modal/py.typed
mlflow_modal_deploy-0.6.0.dist-info/licenses/LICENSE
mlflow_modal_deploy-0.6.0.dist-info/METADATA
mlflow_modal_deploy-0.6.0.dist-info/WHEEL
mlflow_modal_deploy-0.6.0.dist-info/entry_points.txt
mlflow_modal_deploy-0.6.0.dist-info/top_level.txt
mlflow_modal_deploy-0.6.0.dist-info/RECORD
