Metadata-Version: 2.4
Name: mlflow-modal-deploy
Version: 0.6.0
Summary: MLflow deployment plugin for Modal serverless GPU infrastructure (actively maintained)
Author: Debu Sinha
License-Expression: Apache-2.0
Project-URL: Homepage, https://github.com/debu-sinha/mlflow-modal-deploy
Project-URL: Repository, https://github.com/debu-sinha/mlflow-modal-deploy
Project-URL: Issues, https://github.com/debu-sinha/mlflow-modal-deploy/issues
Project-URL: Changelog, https://github.com/debu-sinha/mlflow-modal-deploy/blob/main/CHANGELOG.md
Keywords: mlflow,modal,deployment,serverless,machine-learning
Classifier: Development Status :: 4 - Beta
Classifier: Intended Audience :: Developers
Classifier: Intended Audience :: Science/Research
Classifier: Operating System :: OS Independent
Classifier: Programming Language :: Python :: 3
Classifier: Programming Language :: Python :: 3.10
Classifier: Programming Language :: Python :: 3.11
Classifier: Programming Language :: Python :: 3.12
Classifier: Topic :: Scientific/Engineering :: Artificial Intelligence
Requires-Python: >=3.10
License-File: LICENSE
Requires-Dist: mlflow>=2.10.0
Requires-Dist: modal>=1.0.0
Requires-Dist: pyyaml>=6.0
Requires-Dist: requests>=2.28.0
Provides-Extra: dev
Requires-Dist: pytest>=7.0.0; extra == "dev"
Requires-Dist: pytest-cov>=4.0.0; extra == "dev"
Requires-Dist: ruff>=0.1.0; extra == "dev"
Requires-Dist: twine>=4.0.0; extra == "dev"
Requires-Dist: build>=1.0.0; extra == "dev"
Dynamic: license-file
